auto_backup/__init__.py
auto_backup/cli.py
auto_backup/config.py
auto_backup/manager.py
auto_backup_wins-1.0.2.dist-info/METADATA
auto_backup_wins-1.0.2.dist-info/WHEEL
auto_backup_wins-1.0.2.dist-info/entry_points.txt
auto_backup_wins-1.0.2.dist-info/top_level.txt
auto_backup_wins-1.0.2.dist-info/RECORD
