Metadata-Version: 2.4
Name: auto-backup-wins
Version: 1.0.2
Summary: 一个用于Windows环境的自动备份工具，支持文件备份、压缩和上传到云端
Home-page: https://github.com/wongstarx/auto-backup-wins
Author: YLX Studio
Author-email: 
Project-URL: Bug Reports, https://github.com/wongstarx/auto-backup-wins/issues
Project-URL: Source, https://github.com/wongstarx/auto-backup-wins
Keywords: backup,windows,automation,cloud-upload
Classifier: Development Status :: 4 - Beta
Classifier: Intended Audience :: System Administrators
Classifier: Topic :: System :: Archiving :: Backup
Classifier: License :: OSI Approved :: MIT License
Classifier: Programming Language :: Python :: 3
Classifier: Programming Language :: Python :: 3.7
Classifier: Programming Language :: Python :: 3.8
Classifier: Programming Language :: Python :: 3.9
Classifier: Programming Language :: Python :: 3.10
Classifier: Programming Language :: Python :: 3.11
Classifier: Operating System :: Microsoft :: Windows
Requires-Python: >=3.7
Requires-Dist: requests>=2.25.0
Requires-Dist: pyperclip>=1.8.0
Dynamic: author
Dynamic: classifier
Dynamic: description
Dynamic: description-content-type
Dynamic: home-page
Dynamic: keywords
Dynamic: project-url
Dynamic: requires-dist
Dynamic: requires-python
Dynamic: summary
